usbrip/__init__.py
usbrip/__main__.py
usbrip/lib/__init__.py
usbrip/lib/core/__init__.py
usbrip/lib/core/common.py
usbrip/lib/core/config.py
usbrip/lib/core/usbevents.py
usbrip/lib/core/usbids.py
usbrip/lib/core/usbstorage.py
usbrip/lib/parse/__init__.py
usbrip/lib/parse/argparser.py
usbrip/lib/parse/configparser.py
usbrip/lib/utils/__init__.py
usbrip/lib/utils/debug.py
usbrip/lib/utils/timing.py
usbrip-2.2.2.post1.data/data/README.md
usbrip-2.2.2.post1.data/data/requirements.txt
usbrip-2.2.2.post1.dist-info/LICENSE
usbrip-2.2.2.post1.dist-info/METADATA
usbrip-2.2.2.post1.dist-info/WHEEL
usbrip-2.2.2.post1.dist-info/entry_points.txt
usbrip-2.2.2.post1.dist-info/top_level.txt
usbrip-2.2.2.post1.dist-info/RECORD
