Metadata-Version: 2.1
Name: usbrip
Version: 2.2.2.post1
Summary: USB device artifacts tracker
Home-page: https://github.com/snovvcrash/usbrip
Author: Sam Freeside (@snovvcrash)
Author-email: snovvcrash@protonmail.ch
License: GPL-3.0
Keywords: forensics cybersecurity infosec usb-history usb-devices
Platform: UNKNOWN
Requires-Python: >=3.6
Requires-Dist: termcolor
Requires-Dist: terminaltables
Requires-Dist: tqdm
